mwpermission
