Metadata-Version: 1.1
Name: mwpermission
Version: 0.1.21
Summary: maxwin permission 
Home-page: https://bitbucket.org/maxwin-inc/mwpermission/src
Author: cxhjet
Author-email: cxhjet@qq.com
License: UNKNOWN
Platform: UNKNOWN
Classifier: Intended Audience :: Developers
Classifier: License :: OSI Approved :: BSD License
Classifier: Operating System :: OS Independent
Classifier: Programming Language :: Python :: 3.5
Classifier: Programming Language :: Python :: 3.6
